{
	"format_version": "1.16.100",
	"minecraft:item": {
		"description": {
			"identifier": "mmorpg:sculked_boots",
			"category": "equipment"
		},
		"components": {
			"minecraft:max_stack_size": 1,
			"minecraft:icon": {
				"texture": "mmorpg_sculked_boots"
			},
			"minecraft:armor": {
				"protection": 3
			},
			"minecraft:display_name": {
				"value": "§9Sculked Boots§r\n§o§7+20 Max Mana§r\n§lSet Bonus:§r §7When crouching regenerate mana and take less damage§r\n§7but become blind and very slow§r"
			},
			"minecraft:foil": true,
			"minecraft:wearable": {
				"slot": "slot.armor.feet"
			},
			"minecraft:creative_category": {
				"parent": "itemGroup.name.boots"
			}
		}
	}
}