{
	"format_version": "1.12.0",
	"minecraft:geometry": [
		{
			"description": {
				"identifier": "geometry.core_boss",
				"texture_width": 128,
				"texture_height": 128,
				"visible_bounds_width": 5,
				"visible_bounds_height": 5.5,
				"visible_bounds_offset": [
					0,
					2.25,
					0
				]
			},
			"bones": [
				{
					"name": "Boss",
					"pivot": [
						0,
						3,
						0
					]
				},
				{
					"name": "core",
					"parent": "Boss",
					"pivot": [
						0,
						39,
						0
					],
					"rotation": [
						0,
						-45,
						45
					],
					"cubes": [
						{
							"origin": [
								-9,
								30,
								-9
							],
							"size": [
								18,
								18,
								18
							],
							"uv": {
								"north": {
									"uv": [
										0,
										36
									],
									"uv_size": [
										18,
										18
									]
								},
								"east": {
									"uv": [
										18,
										36
									],
									"uv_size": [
										18,
										18
									]
								},
								"south": {
									"uv": [
										54,
										36
									],
									"uv_size": [
										-18,
										18
									]
								},
								"west": {
									"uv": [
										48,
										18
									],
									"uv_size": [
										18,
										-18
									]
								},
								"up": {
									"uv": [
										66,
										18
									],
									"uv_size": [
										-18,
										18
									]
								},
								"down": {
									"uv": [
										18,
										72
									],
									"uv_size": [
										-18,
										-18
									]
								}
							}
						},
						{
							"origin": [
								-6,
								33,
								-6
							],
							"size": [
								12,
								12,
								12
							],
							"uv": {
								"north": {
									"uv": [
										54,
										56
									],
									"uv_size": [
										12,
										12
									]
								},
								"east": {
									"uv": [
										18,
										64
									],
									"uv_size": [
										12,
										12
									]
								},
								"south": {
									"uv": [
										30,
										64
									],
									"uv_size": [
										12,
										12
									]
								},
								"west": {
									"uv": [
										42,
										64
									],
									"uv_size": [
										12,
										12
									]
								},
								"up": {
									"uv": [
										66,
										0
									],
									"uv_size": [
										12,
										12
									]
								},
								"down": {
									"uv": [
										66,
										24
									],
									"uv_size": [
										12,
										-12
									]
								}
							}
						}
					]
				},
				{
					"name": "shield",
					"parent": "Boss",
					"pivot": [
						0,
						41,
						0
					],
					"cubes": [
						{
							"origin": [
								-12,
								17,
								-22
							],
							"size": [
								24,
								36,
								3
							],
							"uv": {
								"north": {
									"uv": [
										0,
										0
									],
									"uv_size": [
										24,
										36
									]
								},
								"east": {
									"uv": [
										66,
										56
									],
									"uv_size": [
										3,
										36
									]
								},
								"south": {
									"uv": [
										24,
										0
									],
									"uv_size": [
										24,
										36
									]
								},
								"west": {
									"uv": [
										54,
										68
									],
									"uv_size": [
										3,
										36
									]
								},
								"up": {
									"uv": [
										66,
										24
									],
									"uv_size": [
										24,
										3
									]
								},
								"down": {
									"uv": [
										66,
										30
									],
									"uv_size": [
										24,
										-3
									]
								}
							}
						},
						{
							"origin": [
								-9,
								7,
								-22
							],
							"size": [
								18,
								10,
								3
							],
							"uv": {
								"north": {
									"uv": [
										18,
										54
									],
									"uv_size": [
										18,
										10
									]
								},
								"east": {
									"uv": [
										57,
										68
									],
									"uv_size": [
										3,
										10
									]
								},
								"south": {
									"uv": [
										36,
										54
									],
									"uv_size": [
										18,
										10
									]
								},
								"west": {
									"uv": [
										60,
										68
									],
									"uv_size": [
										3,
										10
									]
								},
								"up": {
									"uv": [
										66,
										30
									],
									"uv_size": [
										18,
										3
									]
								},
								"down": {
									"uv": [
										66,
										36
									],
									"uv_size": [
										18,
										-3
									]
								}
							}
						},
						{
							"origin": [
								-9,
								53,
								-22
							],
							"size": [
								18,
								10,
								3
							],
							"uv": {
								"north": {
									"uv": [
										54,
										36
									],
									"uv_size": [
										18,
										10
									]
								},
								"east": {
									"uv": [
										63,
										68
									],
									"uv_size": [
										3,
										10
									]
								},
								"south": {
									"uv": [
										54,
										46
									],
									"uv_size": [
										18,
										10
									]
								},
								"west": {
									"uv": [
										69,
										62
									],
									"uv_size": [
										3,
										10
									]
								},
								"up": {
									"uv": [
										69,
										56
									],
									"uv_size": [
										18,
										3
									]
								},
								"down": {
									"uv": [
										69,
										62
									],
									"uv_size": [
										18,
										-3
									]
								}
							}
						},
						{
							"origin": [
								-12,
								17,
								-22
							],
							"size": [
								24,
								36,
								3
							],
							"pivot": [
								0,
								41.75,
								0
							],
							"rotation": [
								0,
								180,
								0
							],
							"uv": {
								"north": {
									"uv": [
										0,
										0
									],
									"uv_size": [
										24,
										36
									]
								},
								"east": {
									"uv": [
										66,
										56
									],
									"uv_size": [
										3,
										36
									]
								},
								"south": {
									"uv": [
										24,
										0
									],
									"uv_size": [
										24,
										36
									]
								},
								"west": {
									"uv": [
										54,
										68
									],
									"uv_size": [
										3,
										36
									]
								},
								"up": {
									"uv": [
										66,
										24
									],
									"uv_size": [
										24,
										3
									]
								},
								"down": {
									"uv": [
										66,
										30
									],
									"uv_size": [
										24,
										-3
									]
								}
							}
						},
						{
							"origin": [
								-9,
								7,
								-22
							],
							"size": [
								18,
								10,
								3
							],
							"pivot": [
								0,
								33.75,
								0
							],
							"rotation": [
								0,
								180,
								0
							],
							"uv": {
								"north": {
									"uv": [
										18,
										54
									],
									"uv_size": [
										18,
										10
									]
								},
								"east": {
									"uv": [
										57,
										68
									],
									"uv_size": [
										3,
										10
									]
								},
								"south": {
									"uv": [
										36,
										54
									],
									"uv_size": [
										18,
										10
									]
								},
								"west": {
									"uv": [
										60,
										68
									],
									"uv_size": [
										3,
										10
									]
								},
								"up": {
									"uv": [
										66,
										30
									],
									"uv_size": [
										18,
										3
									]
								},
								"down": {
									"uv": [
										66,
										36
									],
									"uv_size": [
										18,
										-3
									]
								}
							}
						},
						{
							"origin": [
								-9,
								53,
								-22
							],
							"size": [
								18,
								10,
								3
							],
							"pivot": [
								0,
								33.75,
								0
							],
							"rotation": [
								0,
								180,
								0
							],
							"uv": {
								"north": {
									"uv": [
										54,
										36
									],
									"uv_size": [
										18,
										10
									]
								},
								"east": {
									"uv": [
										63,
										68
									],
									"uv_size": [
										3,
										10
									]
								},
								"south": {
									"uv": [
										54,
										46
									],
									"uv_size": [
										18,
										10
									]
								},
								"west": {
									"uv": [
										69,
										62
									],
									"uv_size": [
										3,
										10
									]
								},
								"up": {
									"uv": [
										69,
										56
									],
									"uv_size": [
										18,
										3
									]
								},
								"down": {
									"uv": [
										69,
										62
									],
									"uv_size": [
										18,
										-3
									]
								}
							}
						},
						{
							"origin": [
								-12,
								17,
								-22
							],
							"size": [
								24,
								36,
								3
							],
							"pivot": [
								0,
								41.75,
								0
							],
							"rotation": [
								0,
								90,
								0
							],
							"uv": {
								"north": {
									"uv": [
										0,
										0
									],
									"uv_size": [
										24,
										36
									]
								},
								"east": {
									"uv": [
										66,
										56
									],
									"uv_size": [
										3,
										36
									]
								},
								"south": {
									"uv": [
										24,
										0
									],
									"uv_size": [
										24,
										36
									]
								},
								"west": {
									"uv": [
										54,
										68
									],
									"uv_size": [
										3,
										36
									]
								},
								"up": {
									"uv": [
										66,
										24
									],
									"uv_size": [
										24,
										3
									]
								},
								"down": {
									"uv": [
										66,
										30
									],
									"uv_size": [
										24,
										-3
									]
								}
							}
						},
						{
							"origin": [
								-9,
								7,
								-22
							],
							"size": [
								18,
								10,
								3
							],
							"pivot": [
								0,
								33.75,
								0
							],
							"rotation": [
								0,
								90,
								0
							],
							"uv": {
								"north": {
									"uv": [
										18,
										54
									],
									"uv_size": [
										18,
										10
									]
								},
								"east": {
									"uv": [
										57,
										68
									],
									"uv_size": [
										3,
										10
									]
								},
								"south": {
									"uv": [
										36,
										54
									],
									"uv_size": [
										18,
										10
									]
								},
								"west": {
									"uv": [
										60,
										68
									],
									"uv_size": [
										3,
										10
									]
								},
								"up": {
									"uv": [
										66,
										30
									],
									"uv_size": [
										18,
										3
									]
								},
								"down": {
									"uv": [
										66,
										36
									],
									"uv_size": [
										18,
										-3
									]
								}
							}
						},
						{
							"origin": [
								-9,
								53,
								-22
							],
							"size": [
								18,
								10,
								3
							],
							"pivot": [
								0,
								33.75,
								0
							],
							"rotation": [
								0,
								90,
								0
							],
							"uv": {
								"north": {
									"uv": [
										54,
										36
									],
									"uv_size": [
										18,
										10
									]
								},
								"east": {
									"uv": [
										63,
										68
									],
									"uv_size": [
										3,
										10
									]
								},
								"south": {
									"uv": [
										54,
										46
									],
									"uv_size": [
										18,
										10
									]
								},
								"west": {
									"uv": [
										69,
										62
									],
									"uv_size": [
										3,
										10
									]
								},
								"up": {
									"uv": [
										69,
										56
									],
									"uv_size": [
										18,
										3
									]
								},
								"down": {
									"uv": [
										69,
										62
									],
									"uv_size": [
										18,
										-3
									]
								}
							}
						},
						{
							"origin": [
								-9,
								7,
								-22
							],
							"size": [
								18,
								10,
								3
							],
							"pivot": [
								0,
								33.75,
								0
							],
							"rotation": [
								0,
								-90,
								0
							],
							"uv": {
								"north": {
									"uv": [
										18,
										54
									],
									"uv_size": [
										18,
										10
									]
								},
								"east": {
									"uv": [
										57,
										68
									],
									"uv_size": [
										3,
										10
									]
								},
								"south": {
									"uv": [
										36,
										54
									],
									"uv_size": [
										18,
										10
									]
								},
								"west": {
									"uv": [
										60,
										68
									],
									"uv_size": [
										3,
										10
									]
								},
								"up": {
									"uv": [
										66,
										30
									],
									"uv_size": [
										18,
										3
									]
								},
								"down": {
									"uv": [
										66,
										36
									],
									"uv_size": [
										18,
										-3
									]
								}
							}
						},
						{
							"origin": [
								-12,
								17,
								-22
							],
							"size": [
								24,
								36,
								3
							],
							"pivot": [
								0,
								41.75,
								0
							],
							"rotation": [
								0,
								-90,
								0
							],
							"uv": {
								"north": {
									"uv": [
										0,
										0
									],
									"uv_size": [
										24,
										36
									]
								},
								"east": {
									"uv": [
										66,
										56
									],
									"uv_size": [
										3,
										36
									]
								},
								"south": {
									"uv": [
										24,
										0
									],
									"uv_size": [
										24,
										36
									]
								},
								"west": {
									"uv": [
										54,
										68
									],
									"uv_size": [
										3,
										36
									]
								},
								"up": {
									"uv": [
										66,
										24
									],
									"uv_size": [
										24,
										3
									]
								},
								"down": {
									"uv": [
										66,
										30
									],
									"uv_size": [
										24,
										-3
									]
								}
							}
						},
						{
							"origin": [
								-9,
								53,
								-22
							],
							"size": [
								18,
								10,
								3
							],
							"pivot": [
								0,
								33.75,
								0
							],
							"rotation": [
								0,
								-90,
								0
							],
							"uv": {
								"north": {
									"uv": [
										54,
										36
									],
									"uv_size": [
										18,
										10
									]
								},
								"east": {
									"uv": [
										63,
										68
									],
									"uv_size": [
										3,
										10
									]
								},
								"south": {
									"uv": [
										54,
										46
									],
									"uv_size": [
										18,
										10
									]
								},
								"west": {
									"uv": [
										69,
										62
									],
									"uv_size": [
										3,
										10
									]
								},
								"up": {
									"uv": [
										69,
										56
									],
									"uv_size": [
										18,
										3
									]
								},
								"down": {
									"uv": [
										69,
										62
									],
									"uv_size": [
										18,
										-3
									]
								}
							}
						}
					]
				},
				{
					"name": "legs",
					"parent": "Boss",
					"pivot": [
						0,
						24,
						0
					],
					"rotation": [
						0,
						45,
						0
					],
					"cubes": [
						{
							"origin": [
								-1.5,
								16,
								-16.5
							],
							"size": [
								3,
								9,
								3
							],
							"uv": {
								"north": {
									"uv": [
										0,
										72
									],
									"uv_size": [
										3,
										9
									]
								},
								"east": {
									"uv": [
										3,
										72
									],
									"uv_size": [
										3,
										9
									]
								},
								"south": {
									"uv": [
										6,
										72
									],
									"uv_size": [
										3,
										9
									]
								},
								"west": {
									"uv": [
										9,
										72
									],
									"uv_size": [
										3,
										9
									]
								},
								"up": {
									"uv": [
										78,
										0
									],
									"uv_size": [
										3,
										3
									]
								},
								"down": {
									"uv": [
										78,
										6
									],
									"uv_size": [
										3,
										-3
									]
								}
							}
						},
						{
							"origin": [
								-1.5,
								16,
								13.5
							],
							"size": [
								3,
								9,
								3
							],
							"uv": {
								"north": {
									"uv": [
										12,
										72
									],
									"uv_size": [
										3,
										9
									]
								},
								"east": {
									"uv": [
										15,
										72
									],
									"uv_size": [
										3,
										9
									]
								},
								"south": {
									"uv": [
										72,
										36
									],
									"uv_size": [
										3,
										9
									]
								},
								"west": {
									"uv": [
										72,
										45
									],
									"uv_size": [
										3,
										9
									]
								},
								"up": {
									"uv": [
										78,
										6
									],
									"uv_size": [
										3,
										3
									]
								},
								"down": {
									"uv": [
										78,
										12
									],
									"uv_size": [
										3,
										-3
									]
								}
							}
						},
						{
							"origin": [
								-1.5,
								16,
								-16.5
							],
							"size": [
								3,
								9,
								3
							],
							"pivot": [
								0,
								24,
								0
							],
							"rotation": [
								0,
								-90,
								0
							],
							"uv": {
								"north": {
									"uv": [
										72,
										62
									],
									"uv_size": [
										3,
										9
									]
								},
								"east": {
									"uv": [
										69,
										72
									],
									"uv_size": [
										3,
										9
									]
								},
								"south": {
									"uv": [
										72,
										71
									],
									"uv_size": [
										3,
										9
									]
								},
								"west": {
									"uv": [
										75,
										36
									],
									"uv_size": [
										3,
										9
									]
								},
								"up": {
									"uv": [
										78,
										12
									],
									"uv_size": [
										3,
										3
									]
								},
								"down": {
									"uv": [
										78,
										18
									],
									"uv_size": [
										3,
										-3
									]
								}
							}
						},
						{
							"origin": [
								-1.5,
								16,
								13.5
							],
							"size": [
								3,
								9,
								3
							],
							"pivot": [
								0,
								24,
								0
							],
							"rotation": [
								0,
								-90,
								0
							],
							"uv": {
								"north": {
									"uv": [
										75,
										45
									],
									"uv_size": [
										3,
										9
									]
								},
								"east": {
									"uv": [
										75,
										62
									],
									"uv_size": [
										3,
										9
									]
								},
								"south": {
									"uv": [
										75,
										71
									],
									"uv_size": [
										3,
										9
									]
								},
								"west": {
									"uv": [
										18,
										76
									],
									"uv_size": [
										3,
										9
									]
								},
								"up": {
									"uv": [
										78,
										18
									],
									"uv_size": [
										3,
										3
									]
								},
								"down": {
									"uv": [
										78,
										24
									],
									"uv_size": [
										3,
										-3
									]
								}
							}
						}
					]
				},
				{
					"name": "legs2",
					"parent": "Boss",
					"pivot": [
						0,
						10.5,
						0
					],
					"cubes": [
						{
							"origin": [
								-0.7125,
								7.90375,
								-12.375
							],
							"size": [
								2.25,
								6.75,
								2.25
							],
							"uv": {
								"north": {
									"uv": [
										21,
										76
									],
									"uv_size": [
										2,
										7
									]
								},
								"east": {
									"uv": [
										23,
										76
									],
									"uv_size": [
										2,
										7
									]
								},
								"south": {
									"uv": [
										25,
										76
									],
									"uv_size": [
										2,
										7
									]
								},
								"west": {
									"uv": [
										27,
										76
									],
									"uv_size": [
										2,
										7
									]
								},
								"up": {
									"uv": [
										72,
										54
									],
									"uv_size": [
										2,
										2
									]
								},
								"down": {
									"uv": [
										74,
										56
									],
									"uv_size": [
										2,
										-2
									]
								}
							}
						},
						{
							"origin": [
								-0.7125,
								7.90375,
								10.125
							],
							"size": [
								2.25,
								6.75,
								2.25
							],
							"uv": {
								"north": {
									"uv": [
										29,
										76
									],
									"uv_size": [
										2,
										7
									]
								},
								"east": {
									"uv": [
										31,
										76
									],
									"uv_size": [
										2,
										7
									]
								},
								"south": {
									"uv": [
										33,
										76
									],
									"uv_size": [
										2,
										7
									]
								},
								"west": {
									"uv": [
										35,
										76
									],
									"uv_size": [
										2,
										7
									]
								},
								"up": {
									"uv": [
										76,
										54
									],
									"uv_size": [
										2,
										2
									]
								},
								"down": {
									"uv": [
										78,
										38
									],
									"uv_size": [
										2,
										-2
									]
								}
							}
						},
						{
							"origin": [
								-0.7125,
								7.90375,
								-12.375
							],
							"size": [
								2.25,
								6.75,
								2.25
							],
							"pivot": [
								0.4125,
								13.90375,
								0
							],
							"rotation": [
								0,
								-90,
								0
							],
							"uv": {
								"north": {
									"uv": [
										37,
										76
									],
									"uv_size": [
										2,
										7
									]
								},
								"east": {
									"uv": [
										39,
										76
									],
									"uv_size": [
										2,
										7
									]
								},
								"south": {
									"uv": [
										41,
										76
									],
									"uv_size": [
										2,
										7
									]
								},
								"west": {
									"uv": [
										43,
										76
									],
									"uv_size": [
										2,
										7
									]
								},
								"up": {
									"uv": [
										78,
										38
									],
									"uv_size": [
										2,
										2
									]
								},
								"down": {
									"uv": [
										78,
										42
									],
									"uv_size": [
										2,
										-2
									]
								}
							}
						},
						{
							"origin": [
								-0.7125,
								7.90375,
								10.125
							],
							"size": [
								2.25,
								6.75,
								2.25
							],
							"pivot": [
								0.4125,
								13.90375,
								0
							],
							"rotation": [
								0,
								-90,
								0
							],
							"uv": {
								"north": {
									"uv": [
										45,
										76
									],
									"uv_size": [
										2,
										7
									]
								},
								"east": {
									"uv": [
										47,
										76
									],
									"uv_size": [
										2,
										7
									]
								},
								"south": {
									"uv": [
										49,
										76
									],
									"uv_size": [
										2,
										7
									]
								},
								"west": {
									"uv": [
										51,
										76
									],
									"uv_size": [
										2,
										7
									]
								},
								"up": {
									"uv": [
										78,
										42
									],
									"uv_size": [
										2,
										2
									]
								},
								"down": {
									"uv": [
										78,
										46
									],
									"uv_size": [
										2,
										-2
									]
								}
							}
						}
					]
				}
			]
		}
	]
}